usscore.py
usscore-0.0.7.dist-info/METADATA
usscore-0.0.7.dist-info/WHEEL
usscore-0.0.7.dist-info/entry_points.txt
usscore-0.0.7.dist-info/top_level.txt
usscore-0.0.7.dist-info/RECORD
