Metadata-Version: 2.1
Name: usscore
Version: 0.0.7
Summary: PyPI package for scoring state policies of covid-19 in the US
Home-page: https://github.com/y-takefuji/scoreUS
Author: yoshiyasu takefuji
Author-email: takefuji@keio.jp
License: UNKNOWN
Project-URL: Bug Tracker, https://github.com/y-takefuji/scoreUS
Platform: UNKNOWN
Classifier: Programming Language :: Python :: 3
Classifier: License :: OSI Approved :: MIT License
Classifier: Operating System :: OS Independent
Requires-Python: >=3.8
